<?xml version="1.0" encoding="UTF-8"?>
<objects serializationModel="Studio.02.02.00">
	<object class="AudioFile" id="{72ab3c75-c710-45e1-a38d-6f27458c8d4e}">
		<property name="assetPath">
			<value>bonoise_pillar.wav</value>
		</property>
		<property name="isStreaming">
			<value>true</value>
		</property>
		<property name="frequencyInKHz">
			<value>44.0999985</value>
		</property>
		<property name="channelCount">
			<value>2</value>
		</property>
		<property name="length">
			<value>122</value>
		</property>
		<relationship name="masterAssetFolder">
			<destination>{2a19502c-b47c-40cf-84ee-c598ada31671}</destination>
		</relationship>
	</object>
</objects>
